cone.app-1.0.8-py3.9-nspkg.pth
cone/app/__init__.py
cone/app/compat.py
cone/app/configure.zcml
cone/app/interfaces.py
cone/app/model.py
cone/app/security.py
cone/app/ugm.py
cone/app/utils.py
cone/app/workflow.py
cone/app/browser/__init__.py
cone/app/browser/actions.py
cone/app/browser/ajax.py
cone/app/browser/authoring.py
cone/app/browser/batch.py
cone/app/browser/content.py
cone/app/browser/contents.py
cone/app/browser/contextmenu.py
cone/app/browser/copysupport.py
cone/app/browser/exception.py
cone/app/browser/form.py
cone/app/browser/layout.py
cone/app/browser/login.py
cone/app/browser/order.py
cone/app/browser/referencebrowser.py
cone/app/browser/resources.py
cone/app/browser/settings.py
cone/app/browser/sharing.py
cone/app/browser/table.py
cone/app/browser/translation.py
cone/app/browser/utils.py
cone/app/browser/workflow.py
cone/app/browser/static/cookie_functions.js
cone/app/browser/static/favicon.ico
cone/app/browser/static/jquery-1.9.1.js
cone/app/browser/static/jquery-1.9.1.min.js
cone/app/browser/static/jquery.migrate-1.2.1.js
cone/app/browser/static/jquery.migrate-1.2.1.min.js
cone/app/browser/static/print.css
cone/app/browser/static/protected.js
cone/app/browser/static/public.js
cone/app/browser/static/styles.css
cone/app/browser/static/bootstrap/css/bootstrap-theme.css
cone/app/browser/static/bootstrap/css/bootstrap-theme.min.css
cone/app/browser/static/bootstrap/css/bootstrap.css
cone/app/browser/static/bootstrap/css/bootstrap.min.css
cone/app/browser/static/bootstrap/fonts/glyphicons-halflings-regular.eot
cone/app/browser/static/bootstrap/fonts/glyphicons-halflings-regular.svg
cone/app/browser/static/bootstrap/fonts/glyphicons-halflings-regular.ttf
cone/app/browser/static/bootstrap/fonts/glyphicons-halflings-regular.woff
cone/app/browser/static/bootstrap/js/bootstrap.js
cone/app/browser/static/bootstrap/js/bootstrap.min.js
cone/app/browser/static/ionicons/.gitignore
cone/app/browser/static/ionicons/css/ionicons.css
cone_app-1.0.8.dist-info/licenses/LICENSE.rst
cone_app-1.0.8.dist-info/METADATA
cone_app-1.0.8.dist-info/WHEEL
cone_app-1.0.8.dist-info/entry_points.txt
cone_app-1.0.8.dist-info/namespace_packages.txt
cone_app-1.0.8.dist-info/top_level.txt
cone_app-1.0.8.dist-info/RECORD
