Metadata-Version: 2.4
Name: cone.app
Version: 1.0.8
Summary: Web application stub
Home-page: http://github.com/conestack/cone.app
Author: Cone Contributors
Author-email: dev@conestack.org
License: Simplified BSD
Keywords: node pyramid cone web
Classifier: Environment :: Web Environment
Classifier: Programming Language :: Python
Classifier: Topic :: Internet :: WWW/HTTP :: Dynamic Content
License-File: LICENSE.rst
Requires-Dist: setuptools
Requires-Dist: Chameleon
Requires-Dist: node<2.0.0,>=0.9.28
Requires-Dist: node.ext.ugm<2.0.0,>=0.9.13
Requires-Dist: pyramid_zcml
Requires-Dist: bdajax>=1.11
Requires-Dist: cone.tile<2.0.0,>=1.0
Requires-Dist: yafowil<4.0.0,>=2.3.4
Requires-Dist: yafowil.webob<2.0.0
Requires-Dist: yafowil.bootstrap<2.0.0
Requires-Dist: repoze.workflow==1.1
Provides-Extra: lxml
Requires-Dist: lxml; extra == "lxml"
Provides-Extra: yaml
Requires-Dist: yafowil.yaml; extra == "yaml"
Provides-Extra: test
Requires-Dist: lxml; extra == "test"
Requires-Dist: yafowil.yaml; extra == "test"
Requires-Dist: zope.testrunner; extra == "test"
Provides-Extra: docs
Requires-Dist: Sphinx; extra == "docs"
Requires-Dist: sphinx_bootstrap_theme; extra == "docs"
Requires-Dist: repoze.sphinx.autointerface; extra == "docs"
Dynamic: author
Dynamic: author-email
Dynamic: classifier
Dynamic: description
Dynamic: home-page
Dynamic: keywords
Dynamic: license
Dynamic: license-file
Dynamic: provides-extra
Dynamic: requires-dist
Dynamic: summary
